
[
  {
    "time": "8:00AM - 8:50AM",
    "period": "Homeroom",
    "teacher": "Ma'am Maria Bastian"
  },
  {
    "time": "8:50AM - 9:40AM",
    "period": "Homeroom",
    "teacher": "Ma'am Maria Bastian"
  },
  {
    "time": "9:40AM - 10:00AM",
    "period": "Break",
    "teacher": "None"
  },
  {
    "time": "10:00AM - 10:50AM",
    "period": "ALA A",
    "teacher": "ALA Adviser"
  },
  {
    "time": "10:50AM - 11:40AM",
    "period": "ALA A",
    "teacher": "ALA Adviser"
  },
  {
    "time": "11:40AM - 12:30PM",
    "period": "Wellness",
    "teacher": "None"
  },
  {
    "time": "12:30PM - 1:20PM",
    "period": "Lunch",
    "teacher": "None"
  },
  {
    "time": "1:20PM - 2:10PM",
    "period": "ALA B",
    "teacher": "ALA Adviser"
  },
  {
    "time": "2:10PM - 3:00PM",
    "period": "ALA B",
    "teacher": "ALA Adviser"
  },
  {
    "time": "3:00PM - 3:20PM",
    "period": "Break",
    "teacher": "None"
  },
  {
    "time": "3:20PM - 4:10",
    "period": "Flag Ceremony",
    "teacher": "None"
  },
  {
    "time": "4:10PM - 5:00PM",
    "period": "None",
    "teacher": "None"
  }
]